pbmd/__init__.py
pbmd/intCheck.py
pbmd/intHandle.py
pbmd/listHandle.py
pbmd/strCheck.py
pbmd/strHandle.py
pbmd-1.0.0.dist-info/LICENSE
pbmd-1.0.0.dist-info/METADATA
pbmd-1.0.0.dist-info/WHEEL
pbmd-1.0.0.dist-info/top_level.txt
pbmd-1.0.0.dist-info/RECORD
