Metadata-Version: 2.1
Name: pbmd
Version: 1.0.0
Summary: 主要用于字符串、数据对比、数据校验、数据清洗、敏感字符去除的模块
Home-page: https://gitee.com/liumou_site/pbmd
Author: 坐公交也用券
Author-email: liumou.site@qq.com
License: UNKNOWN
Platform: UNKNOWN
Classifier: Programming Language :: Python :: 3
Classifier: License :: OSI Approved :: MIT License
Classifier: Operating System :: OS Independent
Requires-Python: >=3.0
